[
    {
        "data": [
            {
                "y": 0, 
                "x": 0
            }, 
            {
                "y": 0.073782737201568, 
                "x": 0.0
            }, 
            {
                "y": 0.3536933170608324, 
                "x": 32.0
            }, 
            {
                "y": 0.3537037732906842, 
                "x": 96.0
            }, 
            {
                "y": 0.3537183795384734, 
                "x": 160.0
            }, 
            {
                "y": 0.3536974285758638, 
                "x": 224.0
            }, 
            {
                "y": 0.3537003018424597, 
                "x": 288.0
            }, 
            {
                "y": 0.35372077466355784, 
                "x": 352.0
            }, 
            {
                "y": 0.3536998235363891, 
                "x": 416.0
            }, 
            {
                "y": 0.3537026968418964, 
                "x": 480.0
            }, 
            {
                "y": 0.3537228109879468, 
                "x": 544.0
            }, 
            {
                "y": 0.3537001435568356, 
                "x": 608.0
            }, 
            {
                "y": 0.35370473335927927, 
                "x": 672.0
            }, 
            {
                "y": 0.35371933965451413, 
                "x": 736.0
            }, 
            {
                "y": 0.35370253855412864, 
                "x": 800.0
            }, 
            {
                "y": 0.3537071283790065, 
                "x": 864.0
            }, 
            {
                "y": 0.3537217347926011, 
                "x": 928.0
            }, 
            {
                "y": 0.3537049335838562, 
                "x": 992.0
            }, 
            {
                "y": 0.35371503124749415, 
                "x": 1056.0
            }, 
            {
                "y": 0.3537123968466153, 
                "x": 1120.0
            }, 
            {
                "y": 0.3536990286622178, 
                "x": 1184.0
            }, 
            {
                "y": 0.35371155988016034, 
                "x": 1248.0
            }, 
            {
                "y": 0.35371028321139064, 
                "x": 1312.0
            }, 
            {
                "y": 0.35369727374238463, 
                "x": 1376.0
            }, 
            {
                "y": 0.3537060134588469, 
                "x": 1440.0
            }, 
            {
                "y": 0.35371060324014875, 
                "x": 1504.0
            }, 
            {
                "y": 0.35369966870081315, 
                "x": 1568.0
            }, 
            {
                "y": 0.3537042584988089, 
                "x": 1632.0
            }, 
            {
                "y": 0.35371678970600157, 
                "x": 1696.0
            }, 
            {
                "y": 0.35369204735928705, 
                "x": 1760.0
            }, 
            {
                "y": 0.3537066535121053, 
                "x": 1824.0
            }, 
            {
                "y": 0.3537209011046509, 
                "x": 1888.0
            }, 
            {
                "y": 0.35344716264385845, 
                "x": 1952.0
            }, 
            {
                "y": 0.35353479912179664, 
                "x": 2016.0
            }, 
            {
                "y": 0.35356458078934777, 
                "x": 2112.0
            }, 
            {
                "y": 0.3535442128139805, 
                "x": 2208.0
            }, 
            {
                "y": 0.35358097467209354, 
                "x": 2304.0
            }, 
            {
                "y": 0.3536990901811509, 
                "x": 2368.0
            }, 
            {
                "y": 0.353699888505223, 
                "x": 2432.0
            }, 
            {
                "y": 0.3537162111591182, 
                "x": 2496.0
            }, 
            {
                "y": 0.3536956186896021, 
                "x": 2560.0
            }, 
            {
                "y": 0.353702283499062, 
                "x": 2624.0
            }, 
            {
                "y": 0.35371653119329555, 
                "x": 2688.0
            }, 
            {
                "y": 0.3536980136653404, 
                "x": 2752.0
            }, 
            {
                "y": 0.3537043200185408, 
                "x": 2816.0
            }, 
            {
                "y": 0.3537189262933487, 
                "x": 2880.0
            }, 
            {
                "y": 0.35369797529317387, 
                "x": 2944.0
            }, 
            {
                "y": 0.35370084856865247, 
                "x": 3008.0
            }, 
            {
                "y": 0.3537192463324392, 
                "x": 3072.0
            }, 
            {
                "y": 0.3537041617319456, 
                "x": 3136.0
            }, 
            {
                "y": 0.35369322719584917, 
                "x": 3200.0
            }, 
            {
                "y": 0.3537133412267277, 
                "x": 3264.0
            }, 
            {
                "y": 0.3537006902825389, 
                "x": 3328.0
            }, 
            {
                "y": 0.3536973387102818, 
                "x": 3392.0
            }, 
            {
                "y": 0.35370986986453634, 
                "x": 3456.0
            }, 
            {
                "y": 0.35370308528723604, 
                "x": 3520.0
            }, 
            {
                "y": 0.3537056001151164, 
                "x": 3584.0
            }, 
            {
                "y": 0.35371226491410157, 
                "x": 3648.0
            }, 
            {
                "y": 0.3536992553650562, 
                "x": 3712.0
            }, 
            {
                "y": 0.3537059201407081, 
                "x": 3776.0
            }, 
            {
                "y": 0.35371637635079595, 
                "x": 3840.0
            }, 
            {
                "y": 0.35370165035032086, 
                "x": 3904.0
            }, 
            {
                "y": 0.35370244868594997, 
                "x": 3968.0
            }, 
            {
                "y": 0.35371877144875213, 
                "x": 4032.0
            }, 
            {
                "y": 0.3537040453680198, 
                "x": 4096.0
            }, 
            {
                "y": 0.3536986187775564, 
                "x": 4160.0
            }, 
            {
                "y": 0.3537170164203275, 
                "x": 4224.0
            }, 
            {
                "y": 0.3537064404181537, 
                "x": 4288.0
            }, 
            {
                "y": 0.35370101375420004, 
                "x": 4352.0
            }, 
            {
                "y": 0.35371941152695185, 
                "x": 4416.0
            }, 
            {
                "y": 0.35370432691784814, 
                "x": 4480.0
            }, 
            {
                "y": 0.35369925881466835, 
                "x": 4544.0
            }, 
            {
                "y": 0.3537155814417772, 
                "x": 4608.0
            }, 
            {
                "y": 0.35370464694113585, 
                "x": 4672.0
            }, 
            {
                "y": 0.35370165379997964, 
                "x": 4736.0
            }, 
            {
                "y": 0.35371211007276915, 
                "x": 4800.0
            }, 
            {
                "y": 0.35370704195969277, 
                "x": 4864.0
            }, 
            {
                "y": 0.35369782390880017, 
                "x": 4928.0
            }, 
            {
                "y": 0.3537145051526725, 
                "x": 4992.0
            }, 
            {
                "y": 0.35370321201534927, 
                "x": 5056.0
            }, 
            {
                "y": 0.3537002188746793, 
                "x": 5120.0
            }, 
            {
                "y": 0.353716541542628, 
                "x": 5184.0
            }, 
            {
                "y": 0.35369766562539384, 
                "x": 5248.0
            }, 
            {
                "y": 0.35370053889584113, 
                "x": 5312.0
            }, 
            {
                "y": 0.3537168615774031, 
                "x": 5376.0
            }, 
            {
                "y": 0.3537000605891294, 
                "x": 5440.0
            }, 
            {
                "y": 0.353702933898488, 
                "x": 5504.0
            }, 
            {
                "y": 0.3537192566819305, 
                "x": 5568.0
            }, 
            {
                "y": 0.35370417208089744, 
                "x": 5632.0
            }, 
            {
                "y": 0.3536932375445045, 
                "x": 5696.0
            }, 
            {
                "y": 0.3537216518188938, 
                "x": 5760.0
            }, 
            {
                "y": 0.3537065670930234, 
                "x": 5824.0
            }, 
            {
                "y": 0.35369734905900607, 
                "x": 5888.0
            }, 
            {
                "y": 0.35371953798967776, 
                "x": 5952.0
            }, 
            {
                "y": 0.35369894569503474, 
                "x": 6016.0
            }, 
            {
                "y": 0.3536938775727567, 
                "x": 6080.0
            }, 
            {
                "y": 0.35372779951525124, 
                "x": 6144.0
            }, 
            {
                "y": 0.35369719077602474, 
                "x": 6208.0
            }, 
            {
                "y": 0.35369627252491564, 
                "x": 6272.0
            }, 
            {
                "y": 0.35372432822421257, 
                "x": 6336.0
            }, 
            {
                "y": 0.3536954358744292, 
                "x": 6400.0
            }, 
            {
                "y": 0.35369830910864963, 
                "x": 6464.0
            }, 
            {
                "y": 0.3537208568861636, 
                "x": 6528.0
            }, 
            {
                "y": 0.35369783080796846, 
                "x": 6592.0
            }, 
            {
                "y": 0.35369655419595664, 
                "x": 6656.0
            }, 
            {
                "y": 0.35372081813271083, 
                "x": 6720.0
            }, 
            {
                "y": 0.3536960759000219, 
                "x": 6784.0
            }, 
            {
                "y": 0.35370481557715494, 
                "x": 6848.0
            }, 
            {
                "y": 0.35371319673615764, 
                "x": 6912.0
            }, 
            {
                "y": 0.3536926044176475, 
                "x": 6976.0
            }, 
            {
                "y": 0.3537072105979956, 
                "x": 7040.0
            }, 
            {
                "y": 0.35372145820770207, 
                "x": 7104.0
            }, 
            {
                "y": 0.35369292443033834, 
                "x": 7168.0
            }, 
            {
                "y": 0.3537013056982672, 
                "x": 7232.0
            }, 
            {
                "y": 0.35371798687838535, 
                "x": 7296.0
            }, 
            {
                "y": 0.35369531936958937, 
                "x": 7360.0
            }, 
            {
                "y": 0.3537037006715755, 
                "x": 7424.0
            }, 
            {
                "y": 0.3537203819981521, 
                "x": 7488.0
            }, 
            {
                "y": 0.353697355958156, 
                "x": 7552.0
            }, 
            {
                "y": 0.3537019457344878, 
                "x": 7616.0
            }, 
            {
                "y": 0.3537144768545226, 
                "x": 7680.0
            }, 
            {
                "y": 0.3536956010549212, 
                "x": 7744.0
            }, 
            {
                "y": 0.3537043407164636, 
                "x": 7808.0
            }, 
            {
                "y": 0.35371479688556157, 
                "x": 7872.0
            }, 
            {
                "y": 0.35369212957399226, 
                "x": 7936.0
            }, 
            {
                "y": 0.35370466073977636, 
                "x": 8000.0
            }, 
            {
                "y": 0.3537171919621278, 
                "x": 8064.0
            }, 
            {
                "y": 0.35369452450247896, 
                "x": 8128.0
            }, 
            {
                "y": 0.35370705575852013, 
                "x": 8192.0
            }, 
            {
                "y": 0.3537195870711295, 
                "x": 8256.0
            }, 
            {
                "y": 0.35369691946339915, 
                "x": 8320.0
            }, 
            {
                "y": 0.35370737578674594, 
                "x": 8384.0
            }, 
            {
                "y": 0.3537219822125671, 
                "x": 8448.0
            }, 
            {
                "y": 0.35369895604385293, 
                "x": 8512.0
            }, 
            {
                "y": 0.3535530932205806, 
                "x": 8576.0
            }, 
            {
                "y": 0.3537102105908132, 
                "x": 8640.0
            }, 
            {
                "y": 0.3537030675282619, 
                "x": 8704.0
            }, 
            {
                "y": 0.35370214935934197, 
                "x": 8768.0
            }, 
            {
                "y": 0.3537143220138216, 
                "x": 8832.0
            }, 
            {
                "y": 0.35369959608218543, 
                "x": 8896.0
            }, 
            {
                "y": 0.3536962445306649, 
                "x": 8960.0
            }, 
            {
                "y": 0.35371671708395697, 
                "x": 9024.0
            }, 
            {
                "y": 0.3537019910720642, 
                "x": 9088.0
            }, 
            {
                "y": 0.35369656454463494, 
                "x": 9152.0
            }, 
            {
                "y": 0.3537191121865275, 
                "x": 9216.0
            }, 
            {
                "y": 0.353389314068258, 
                "x": 9280.0
            }, 
            {
                "y": 0.35358749727242866, 
                "x": 9344.0
            }, 
            {
                "y": 0.35369768287329983, 
                "x": 9408.0
            }, 
            {
                "y": 0.35370055614402734, 
                "x": 9472.0
            }, 
            {
                "y": 0.353716878826323, 
                "x": 9536.0
            }, 
            {
                "y": 0.3537000778372689, 
                "x": 9600.0
            }, 
            {
                "y": 0.3537029511469078, 
                "x": 9664.0
            }, 
            {
                "y": 0.35371927393108404, 
                "x": 9728.0
            }, 
            {
                "y": 0.35370418932915193, 
                "x": 9792.0
            }, 
            {
                "y": 0.35369325479226466, 
                "x": 9856.0
            }, 
            {
                "y": 0.35372166906828095, 
                "x": 9920.0
            }, 
            {
                "y": 0.35370658434151153, 
                "x": 9984.0
            }, 
            {
                "y": 0.35369736630688114, 
                "x": 10048.0
            }, 
            {
                "y": 0.35371955523857257, 
                "x": 10112.0
            }, 
            {
                "y": 0.3536989629430655, 
                "x": 10176.0
            }, 
            {
                "y": 0.3536938948205793, 
                "x": 10240.0
            }, 
            {
                "y": 0.35372781676466575, 
                "x": 10304.0
            }, 
            {
                "y": 0.35369720802388444, 
                "x": 10368.0
            }, 
            {
                "y": 0.3536962897729718, 
                "x": 10432.0
            }, 
            {
                "y": 0.3537243454735746, 
                "x": 10496.0
            }, 
            {
                "y": 0.3536954531221177, 
                "x": 10560.0
            }, 
            {
                "y": 0.35369832635661835, 
                "x": 10624.0
            }, 
            {
                "y": 0.3537208741354732, 
                "x": 10688.0
            }, 
            {
                "y": 0.35369784805589066, 
                "x": 10752.0
            }, 
            {
                "y": 0.3536965714437542, 
                "x": 10816.0
            }, 
            {
                "y": 0.35372083538173055, 
                "x": 10880.0
            }, 
            {
                "y": 0.3536960931477728, 
                "x": 10944.0
            }, 
            {
                "y": 0.35370483282547216, 
                "x": 11008.0
            }, 
            {
                "y": 0.35371321398472017, 
                "x": 11072.0
            }, 
            {
                "y": 0.35369262166534593, 
                "x": 11136.0
            }, 
            {
                "y": 0.3537072278465464, 
                "x": 11200.0
            }, 
            {
                "y": 0.3537214754567842, 
                "x": 11264.0
            }, 
            {
                "y": 0.353692941678068, 
                "x": 11328.0
            }, 
            {
                "y": 0.35370132294624207, 
                "x": 11392.0
            }, 
            {
                "y": 0.353718004127415, 
                "x": 11456.0
            }, 
            {
                "y": 0.3536953366175527, 
                "x": 11520.0
            }, 
            {
                "y": 0.35370371791978406, 
                "x": 11584.0
            }, 
            {
                "y": 0.35372039924741544, 
                "x": 11648.0
            }, 
            {
                "y": 0.35369737320603173, 
                "x": 11712.0
            }, 
            {
                "y": 0.3537019629825251, 
                "x": 11776.0
            }, 
            {
                "y": 0.35371449410320993, 
                "x": 11840.0
            }, 
            {
                "y": 0.3536956183026258, 
                "x": 11904.0
            }, 
            {
                "y": 0.35370435796473454, 
                "x": 11968.0
            }, 
            {
                "y": 0.35371481413428013, 
                "x": 12032.0
            }, 
            {
                "y": 0.35369214682164435, 
                "x": 12096.0
            }, 
            {
                "y": 0.3537046779880785, 
                "x": 12160.0
            }, 
            {
                "y": 0.35371720921108, 
                "x": 12224.0
            }, 
            {
                "y": 0.35369454175036463, 
                "x": 12288.0
            }, 
            {
                "y": 0.3537070730070559, 
                "x": 12352.0
            }, 
            {
                "y": 0.35371960432031524, 
                "x": 12416.0
            }, 
            {
                "y": 0.35369693671151836, 
                "x": 12480.0
            }, 
            {
                "y": 0.35370739303531284, 
                "x": 12544.0
            }, 
            {
                "y": 0.35372199946198646, 
                "x": 12608.0
            }, 
            {
                "y": 0.35369897329188477, 
                "x": 12672.0
            }, 
            {
                "y": 0.35370356308336653, 
                "x": 12736.0
            }, 
            {
                "y": 0.3537160942643522, 
                "x": 12800.0
            }, 
            {
                "y": 0.3536913519687933, 
                "x": 12864.0
            }, 
            {
                "y": 0.3537059580872452, 
                "x": 12928.0
            }, 
            {
                "y": 0.35371641429831785, 
                "x": 12992.0
            }, 
            {
                "y": 0.35369374688674937, 
                "x": 13056.0
            }, 
            {
                "y": 0.35370420312775674, 
                "x": 13120.0
            }, 
            {
                "y": 0.35371880939678796, 
                "x": 13184.0
            }, 
            {
                "y": 0.3536978584046447, 
                "x": 13248.0
            }, 
            {
                "y": 0.3537007316782241, 
                "x": 13312.0
            }, 
            {
                "y": 0.3537208457311432, 
                "x": 13376.0
            }, 
            {
                "y": 0.3537002533709909, 
                "x": 13440.0
            }, 
            {
                "y": 0.35370312668348175, 
                "x": 13504.0
            }, 
            {
                "y": 0.35372324084990286, 
                "x": 13568.0
            }, 
            {
                "y": 0.35370057339221517, 
                "x": 13632.0
            }, 
            {
                "y": 0.35370516319868517, 
                "x": 13696.0
            }, 
            {
                "y": 0.3537197695151623, 
                "x": 13760.0
            }, 
            {
                "y": 0.3537029683953293, 
                "x": 13824.0
            }, 
            {
                "y": 0.35370548322348627, 
                "x": 13888.0
            }, 
            {
                "y": 0.35371629813341093, 
                "x": 13952.0
            }, 
            {
                "y": 0.3537053634308781, 
                "x": 14016.0
            }, 
            {
                "y": 0.35371546109767077, 
                "x": 14080.0
            }, 
            {
                "y": 0.3537128267046476, 
                "x": 14144.0
            }, 
            {
                "y": 0.353697383554758, 
                "x": 14208.0
            }, 
            {
                "y": 0.3537119897290289, 
                "x": 14272.0
            }, 
            {
                "y": 0.3537107130571563, 
                "x": 14336.0
            }, 
            {
                "y": 0.35369770357078917, 
                "x": 14400.0
            }, 
            {
                "y": 0.353706443301364, 
                "x": 14464.0
            }, 
            {
                "y": 0.35371482448351205, 
                "x": 14528.0
            }, 
            {
                "y": 0.3536942320834606, 
                "x": 14592.0
            }, 
            {
                "y": 0.35370468833706065, 
                "x": 14656.0
            }, 
            {
                "y": 0.3537172195604522, 
                "x": 14720.0
            }, 
            {
                "y": 0.353692477182118, 
                "x": 14784.0
            }, 
            {
                "y": 0.3537070833561781, 
                "x": 14848.0
            }, 
            {
                "y": 0.35372133096196495, 
                "x": 14912.0
            }, 
            {
                "y": 0.35369279719457863, 
                "x": 14976.0
            }, 
            {
                "y": 0.3537032534109382, 
                "x": 15040.0
            }, 
            {
                "y": 0.3537157845802536, 
                "x": 15104.0
            }, 
            {
                "y": 0.35369519213210665, 
                "x": 15168.0
            }, 
            {
                "y": 0.35370564841062324, 
                "x": 15232.0
            }, 
            {
                "y": 0.35371817967019575, 
                "x": 15296.0
            }, 
            {
                "y": 0.35369136231733894, 
                "x": 15360.0
            }, 
            {
                "y": 0.3537097598714277, 
                "x": 15424.0
            }, 
            {
                "y": 0.3537164246476434, 
                "x": 15488.0
            }, 
            {
                "y": 0.3536916823277822, 
                "x": 15552.0
            }, 
            {
                "y": 0.35370628846256047, 
                "x": 15616.0
            }, 
            {
                "y": 0.35371881974625374, 
                "x": 15680.0
            }, 
            {
                "y": 0.35368992745174116, 
                "x": 15744.0
            }, 
            {
                "y": 0.3537024585345346, 
                "x": 15808.0
            }, 
            {
                "y": 0.35371291465478527, 
                "x": 15872.0
            }, 
            {
                "y": 0.3536864559305032, 
                "x": 15936.0
            }, 
            {
                "y": 0.3537107199565986, 
                "x": 16000.0
            }, 
            {
                "y": 0.35371530970586157, 
                "x": 16064.0
            }, 
            {
                "y": 0.35368885082187773, 
                "x": 16128.0
            }, 
            {
                "y": 0.3537068899961261, 
                "x": 16192.0
            }, 
            {
                "y": 0.3537135547117886, 
                "x": 16256.0
            }, 
            {
                "y": 0.35369124574568517, 
                "x": 16320.0
            }, 
            {
                "y": 0.35370928500533666, 
                "x": 16384.0
            }, 
            {
                "y": 0.35371594977153287, 
                "x": 16448.0
            }, 
            {
                "y": 0.35369120748660277, 
                "x": 16512.0
            }, 
            {
                "y": 0.35370581359791436, 
                "x": 16576.0
            }, 
            {
                "y": 0.35371419477110844, 
                "x": 16640.0
            }, 
            {
                "y": 0.35369152749676586, 
                "x": 16704.0
            }, 
            {
                "y": 0.353701983680172, 
                "x": 16768.0
            }, 
            {
                "y": 0.35371658983952053, 
                "x": 16832.0
            }, 
            {
                "y": 0.35369392241709896, 
                "x": 16896.0
            }, 
            {
                "y": 0.35371024508792953, 
                "x": 16960.0
            }, 
            {
                "y": 0.3537110434358745, 
                "x": 17024.0
            }, 
            {
                "y": 0.3536963173698653, 
                "x": 17088.0
            }, 
            {
                "y": 0.35371264014257625, 
                "x": 17152.0
            }, 
            {
                "y": 0.3537134385013329, 
                "x": 17216.0
            }, 
            {
                "y": 0.35369663738927504, 
                "x": 17280.0
            }, 
            {
                "y": 0.3537108851458871, 
                "x": 17344.0
            }, 
            {
                "y": 0.35371547489669725, 
                "x": 17408.0
            }, 
            {
                "y": 0.3536907326466983, 
                "x": 17472.0
            }, 
            {
                "y": 0.35371914668480803, 
                "x": 17536.0
            }, 
            {
                "y": 0.3537078535153827, 
                "x": 17600.0
            }, 
            {
                "y": 0.35368726112300924, 
                "x": 17664.0
            }, 
            {
                "y": 0.3537153166053687, 
                "x": 17728.0
            }, 
            {
                "y": 0.3537102485376415, 
                "x": 17792.0
            }, 
            {
                "y": 0.3536913726658851, 
                "x": 17856.0
            }, 
            {
                "y": 0.3537118452371666, 
                "x": 17920.0
            }, 
            {
                "y": 0.35371264359233495, 
                "x": 17984.0
            }, 
            {
                "y": 0.35354882479185495, 
                "x": 18048.0
            }, 
            {
                "y": 0.3536983574029663, 
                "x": 18112.0
            }, 
            {
                "y": 0.3537108885956115, 
                "x": 18176.0
            }, 
            {
                "y": 0.3537037455169211, 
                "x": 18240.0
            }, 
            {
                "y": 0.3537007523760703, 
                "x": 18304.0
            }, 
            {
                "y": 0.35371292500390605, 
                "x": 18368.0
            }, 
            {
                "y": 0.35370027406878113, 
                "x": 18432.0
            }, 
            {
                "y": 0.3537031473816083, 
                "x": 18496.0
            }, 
            {
                "y": 0.3537153200551225, 
                "x": 18560.0
            }, 
            {
                "y": 0.3537026690678416, 
                "x": 18624.0
            }, 
            {
                "y": 0.35370310892381696, 
                "x": 18688.0
            }, 
            {
                "y": 0.35327773124897527, 
                "x": 18752.0
            }, 
            {
                "y": 0.3537047055853655, 
                "x": 18816.0
            }, 
            {
                "y": 0.353717236809407, 
                "x": 18880.0
            }, 
            {
                "y": 0.35369249442980405, 
                "x": 18944.0
            }, 
            {
                "y": 0.35370710060471655, 
                "x": 19008.0
            }, 
            {
                "y": 0.35372134821103474, 
                "x": 19072.0
            }, 
            {
                "y": 0.3536928144422959, 
                "x": 19136.0
            }, 
            {
                "y": 0.35370327065910306, 
                "x": 19200.0
            }, 
            {
                "y": 0.3537158018290684, 
                "x": 19264.0
            }, 
            {
                "y": 0.3536952093800575, 
                "x": 19328.0
            }, 
            {
                "y": 0.3537056656590217, 
                "x": 19392.0
            }, 
            {
                "y": 0.35371819691924417, 
                "x": 19456.0
            }, 
            {
                "y": 0.3536913795649162, 
                "x": 19520.0
            }, 
            {
                "y": 0.35370977711994117, 
                "x": 19584.0
            }, 
            {
                "y": 0.3537164418965208, 
                "x": 19648.0
            }, 
            {
                "y": 0.35369169957539065, 
                "x": 19712.0
            }, 
            {
                "y": 0.3537063057110213, 
                "x": 19776.0
            }, 
            {
                "y": 0.3537188369953646, 
                "x": 19840.0
            }, 
            {
                "y": 0.3536899446991785, 
                "x": 19904.0
            }, 
            {
                "y": 0.3537024757826219, 
                "x": 19968.0
            }, 
            {
                "y": 0.3537129319033202, 
                "x": 20032.0
            }, 
            {
                "y": 0.35368647317788804, 
                "x": 20096.0
            }, 
            {
                "y": 0.35371073720520557, 
                "x": 20160.0
            }, 
            {
                "y": 0.3537153269546302, 
                "x": 20224.0
            }, 
            {
                "y": 0.3536888680694961, 
                "x": 20288.0
            }, 
            {
                "y": 0.3537069072443596, 
                "x": 20352.0
            }, 
            {
                "y": 0.3537135719603861, 
                "x": 20416.0
            }, 
            {
                "y": 0.3536912629935372, 
                "x": 20480.0
            }, 
            {
                "y": 0.3537093022538037, 
                "x": 20544.0
            }, 
            {
                "y": 0.35371596702036384, 
                "x": 20608.0
            }, 
            {
                "y": 0.353691224734165, 
                "x": 20672.0
            }, 
            {
                "y": 0.35370583084632895, 
                "x": 20736.0
            }, 
            {
                "y": 0.3537142120197683, 
                "x": 20800.0
            }, 
            {
                "y": 0.3536915447443592, 
                "x": 20864.0
            }, 
            {
                "y": 0.3537020009282131, 
                "x": 20928.0
            }, 
            {
                "y": 0.353716607088414, 
                "x": 20992.0
            }, 
            {
                "y": 0.35369393966492596, 
                "x": 21056.0
            }, 
            {
                "y": 0.3537102623364902, 
                "x": 21120.0
            }, 
            {
                "y": 0.3537110606845132, 
                "x": 21184.0
            }, 
            {
                "y": 0.35369633461792593, 
                "x": 21248.0
            }, 
            {
                "y": 0.35371265739137053, 
                "x": 21312.0
            }, 
            {
                "y": 0.353713455750205, 
                "x": 21376.0
            }, 
            {
                "y": 0.3536966546373668, 
                "x": 21440.0
            }, 
            {
                "y": 0.3537109023945102, 
                "x": 21504.0
            }, 
            {
                "y": 0.353715492145482, 
                "x": 21568.0
            }, 
            {
                "y": 0.35369074989421423, 
                "x": 21632.0
            }, 
            {
                "y": 0.3537191639339508, 
                "x": 21696.0
            }, 
            {
                "y": 0.35370787076371013, 
                "x": 21760.0
            }, 
            {
                "y": 0.35368727837047265, 
                "x": 21824.0
            }, 
            {
                "y": 0.35371533385413795, 
                "x": 21888.0
            }, 
            {
                "y": 0.35371026578620257, 
                "x": 21952.0
            }, 
            {
                "y": 0.3536913899134634, 
                "x": 22016.0
            }, 
            {
                "y": 0.35371186248588343, 
                "x": 22080.0
            }, 
            {
                "y": 0.35371266084112957, 
                "x": 22144.0
            }, 
            {
                "y": 0.35369378483193326, 
                "x": 22208.0
            }, 
            {
                "y": 0.35372012405424985, 
                "x": 22272.0
            }, 
            {
                "y": 0.3537091894234343, 
                "x": 22336.0
            }, 
            {
                "y": 0.35369617978283635, 
                "x": 22400.0
            }, 
            {
                "y": 0.35372251920295966, 
                "x": 22464.0
            }, 
            {
                "y": 0.35371122587411985, 
                "x": 22528.0
            }, 
            {
                "y": 0.3536923499466801, 
                "x": 22592.0
            }, 
            {
                "y": 0.3537166139879718, 
                "x": 22656.0
            }, 
            {
                "y": 0.3537036044790375, 
                "x": 22720.0
            }, 
            {
                "y": 0.3536947448781512, 
                "x": 22784.0
            }, 
            {
                "y": 0.35372280046178717, 
                "x": 22848.0
            }, 
            {
                "y": 0.35370013303132686, 
                "x": 22912.0
            }, 
            {
                "y": 0.35369298997171994, 
                "x": 22976.0
            }, 
            {
                "y": 0.35372312050258037, 
                "x": 23040.0
            }, 
            {
                "y": 0.3537042445235775, 
                "x": 23104.0
            }, 
            {
                "y": 0.35368951844115964, 
                "x": 23168.0
            }, 
            {
                "y": 0.3537213654601061, 
                "x": 23232.0
            }, 
            {
                "y": 0.35370663953668463, 
                "x": 23296.0
            }, 
            {
                "y": 0.3536957049295809, 
                "x": 23360.0
            }, 
            {
                "y": 0.35372376058590416, 
                "x": 23424.0
            }, 
            {
                "y": 0.35370695956415715, 
                "x": 23488.0
            }, 
            {
                "y": 0.35369187510370814, 
                "x": 23552.0
            }, 
            {
                "y": 0.35372028924958243, 
                "x": 23616.0
            }, 
            {
                "y": 0.35370935461403297, 
                "x": 23680.0
            }, 
            {
                "y": 0.35369427002874876, 
                "x": 23744.0
            }, 
            {
                "y": 0.3537226844005294, 
                "x": 23808.0
            }, 
            {
                "y": 0.35370931605257855, 
                "x": 23872.0
            }, 
            {
                "y": 0.35369459004445364, 
                "x": 23936.0
            }, 
            {
                "y": 0.35371921300990905, 
                "x": 24000.0
            }, 
            {
                "y": 0.35370963607958655, 
                "x": 24064.0
            }, 
            {
                "y": 0.3536969850062613, 
                "x": 24128.0
            }, 
            {
                "y": 0.35372089057860484, 
                "x": 24192.0
            }, 
            {
                "y": 0.35370408968669886, 
                "x": 24256.0
            }, 
            {
                "y": 0.3536893636094698, 
                "x": 24320.0
            }, 
            {
                "y": 0.3537232856979719, 
                "x": 24384.0
            }, 
            {
                "y": 0.3537064846977092, 
                "x": 24448.0
            }, 
            {
                "y": 0.3536934751663547, 
                "x": 24512.0
            }, 
            {
                "y": 0.3537256808497748, 
                "x": 24576.0
            }, 
            {
                "y": 0.35370472973299505, 
                "x": 24640.0
            }, 
            {
                "y": 0.3536900036343174, 
                "x": 24704.0
            }, 
            {
                "y": 0.35372185069235385, 
                "x": 24768.0
            }, 
            {
                "y": 0.3537050497570117, 
                "x": 24832.0
            }, 
            {
                "y": 0.35369239857373697, 
                "x": 24896.0
            }, 
            {
                "y": 0.35372217073142836, 
                "x": 24960.0
            }, 
            {
                "y": 0.353701219855811, 
                "x": 25024.0
            }, 
            {
                "y": 0.353692360295284, 
                "x": 25088.0
            }, 
            {
                "y": 0.3537186993999437, 
                "x": 25152.0
            }, 
            {
                "y": 0.35370361482795687, 
                "x": 25216.0
            }, 
            {
                "y": 0.35369647180394076, 
                "x": 25280.0
            }, 
            {
                "y": 0.3537152280214484, 
                "x": 25344.0
            }, 
            {
                "y": 0.3537098012678627, 
                "x": 25408.0
            }, 
            {
                "y": 0.35369300032036144, 
                "x": 25472.0
            }, 
            {
                "y": 0.35371518936194, 
                "x": 25536.0
            }, 
            {
                "y": 0.35370217991054437, 
                "x": 25600.0
            }, 
            {
                "y": 0.3537012617315108, 
                "x": 25664.0
            }, 
            {
                "y": 0.3537134343690612, 
                "x": 25728.0
            }, 
            {
                "y": 0.35369870846716933, 
                "x": 25792.0
            }, 
            {
                "y": 0.35369535693247023, 
                "x": 25856.0
            }, 
            {
                "y": 0.3537158294271758, 
                "x": 25920.0
            }, 
            {
                "y": 0.35370110344502764, 
                "x": 25984.0
            }, 
            {
                "y": 0.35369567694483417, 
                "x": 26048.0
            }, 
            {
                "y": 0.3537182245177252, 
                "x": 26112.0
            }, 
            {
                "y": 0.35369519865127186, 
                "x": 26176.0
            }, 
            {
                "y": 0.35369807188163815, 
                "x": 26240.0
            }, 
            {
                "y": 0.3537206196407103, 
                "x": 26304.0
            }, 
            {
                "y": 0.3537034599916295, 
                "x": 26368.0
            }, 
            {
                "y": 0.3537004668508755, 
                "x": 26432.0
            }, 
            {
                "y": 0.3537147144891461, 
                "x": 26496.0
            }, 
            {
                "y": 0.35370378001334846, 
                "x": 26560.0
            }, 
            {
                "y": 0.3537028618525467, 
                "x": 26624.0
            }, 
            {
                "y": 0.3537209009280208, 
                "x": 26688.0
            }, 
            {
                "y": 0.35369444211004214, 
                "x": 26752.0
            }, 
            {
                "y": 0.35369903193520563, 
                "x": 26816.0
            }, 
            {
                "y": 0.3537174296003997, 
                "x": 26880.0
            }, 
            {
                "y": 0.3536968370698465, 
                "x": 26944.0
            }, 
            {
                "y": 0.3537031434201202, 
                "x": 27008.0
            }, 
            {
                "y": 0.353713958225768, 
                "x": 27072.0
            }, 
            {
                "y": 0.3536971570901966, 
                "x": 27136.0
            }, 
            {
                "y": 0.35370553841831576, 
                "x": 27200.0
            }, 
            {
                "y": 0.35371599461849695, 
                "x": 27264.0
            }, 
            {
                "y": 0.35369125233026794, 
                "x": 27328.0
            }, 
            {
                "y": 0.3537079334489454, 
                "x": 27392.0
            }, 
            {
                "y": 0.3537142396176275, 
                "x": 27456.0
            }, 
            {
                "y": 0.353551134364919, 
                "x": 27520.0
            }, 
            {
                "y": 0.35369823706459236, 
                "x": 27584.0
            }, 
            {
                "y": 0.3536969604496478, 
                "x": 27648.0
            }, 
            {
                "y": 0.35372122441518844, 
                "x": 27712.0
            }, 
            {
                "y": 0.35369648215261434, 
                "x": 27776.0
            }, 
            {
                "y": 0.353705221843086, 
                "x": 27840.0
            }, 
            {
                "y": 0.3537136030078656, 
                "x": 27904.0
            }, 
            {
                "y": 0.3536930106690034, 
                "x": 27968.0
            }, 
            {
                "y": 0.3537076168694285, 
                "x": 28032.0
            }, 
            {
                "y": 0.35372186449165005, 
                "x": 28096.0
            }, 
            {
                "y": 0.35369333068242936, 
                "x": 28160.0
            }, 
            {
                "y": 0.3532814050000129, 
                "x": 28224.0
            }, 
            {
                "y": 0.3536970022543869, 
                "x": 28288.0
            }, 
            {
                "y": 0.3537209078276317, 
                "x": 28352.0
            }, 
            {
                "y": 0.35370410693494536, 
                "x": 28416.0
            }, 
            {
                "y": 0.35368938085713825, 
                "x": 28480.0
            }, 
            {
                "y": 0.3537233029472323, 
                "x": 28544.0
            }, 
            {
                "y": 0.3537065019461892, 
                "x": 28608.0
            }, 
            {
                "y": 0.353693492414138, 
                "x": 28672.0
            }, 
            {
                "y": 0.3537256980992688, 
                "x": 28736.0
            }, 
            {
                "y": 0.3537047469813039, 
                "x": 28800.0
            }, 
            {
                "y": 0.35369002088204826, 
                "x": 28864.0
            }, 
            {
                "y": 0.3537218679414743, 
                "x": 28928.0
            }, 
            {
                "y": 0.35370506700535176, 
                "x": 28992.0
            }, 
            {
                "y": 0.35369241582170136, 
                "x": 29056.0
            }, 
            {
                "y": 0.35372218798058, 
                "x": 29120.0
            }, 
            {
                "y": 0.35370123710377754, 
                "x": 29184.0
            }, 
            {
                "y": 0.35369237754295874, 
                "x": 29248.0
            }, 
            {
                "y": 0.353718716649043, 
                "x": 29312.0
            }, 
            {
                "y": 0.35370363207615696, 
                "x": 29376.0
            }, 
            {
                "y": 0.35369648905173023, 
                "x": 29440.0
            }, 
            {
                "y": 0.353715245270495, 
                "x": 29504.0
            }, 
            {
                "y": 0.35370981851638017, 
                "x": 29568.0
            }, 
            {
                "y": 0.35369301756809846, 
                "x": 29632.0
            }, 
            {
                "y": 0.35371520661069683, 
                "x": 29696.0
            }, 
            {
                "y": 0.3537021971586045, 
                "x": 29760.0
            }, 
            {
                "y": 0.3537012789797675, 
                "x": 29824.0
            }, 
            {
                "y": 0.3537134516176469, 
                "x": 29888.0
            }, 
            {
                "y": 0.35369872571517696, 
                "x": 29952.0
            }, 
            {
                "y": 0.3536953741801511, 
                "x": 30016.0
            }, 
            {
                "y": 0.3537158466759951, 
                "x": 30080.0
            }, 
            {
                "y": 0.3537011206932689, 
                "x": 30144.0
            }, 
            {
                "y": 0.35369569419254615, 
                "x": 30208.0
            }, 
            {
                "y": 0.3537182417667781, 
                "x": 30272.0
            }, 
            {
                "y": 0.3536952158989372, 
                "x": 30336.0
            }, 
            {
                "y": 0.3536980891295838, 
                "x": 30400.0
            }, 
            {
                "y": 0.3537206368899967, 
                "x": 30464.0
            }, 
            {
                "y": 0.35370347723981455, 
                "x": 30528.0
            }, 
            {
                "y": 0.35370048409905464, 
                "x": 30592.0
            }, 
            {
                "y": 0.35371473173785667, 
                "x": 30656.0
            }, 
            {
                "y": 0.3537037972615647, 
                "x": 30720.0
            }, 
            {
                "y": 0.3537028791009595, 
                "x": 30784.0
            }, 
            {
                "y": 0.3537209181770486, 
                "x": 30848.0
            }, 
            {
                "y": 0.3536944593579198, 
                "x": 30912.0
            }, 
            {
                "y": 0.35369904918324485, 
                "x": 30976.0
            }, 
            {
                "y": 0.35371744684937495, 
                "x": 31040.0
            }, 
            {
                "y": 0.3536968543179577, 
                "x": 31104.0
            }, 
            {
                "y": 0.35370316066827434, 
                "x": 31168.0
            }, 
            {
                "y": 0.3537139754746908, 
                "x": 31232.0
            }, 
            {
                "y": 0.353697174338339, 
                "x": 31296.0
            }, 
            {
                "y": 0.3537055556667035, 
                "x": 31360.0
            }, 
            {
                "y": 0.35371601186733226, 
                "x": 31424.0
            }, 
            {
                "y": 0.3536912695778345, 
                "x": 31488.0
            }, 
            {
                "y": 0.3537079506975667, 
                "x": 31552.0
            }, 
            {
                "y": 0.3537142568662917, 
                "x": 31616.0
            }, 
            {
                "y": 0.3536995309368386, 
                "x": 31680.0
            }, 
            {
                "y": 0.3537041207335438, 
                "x": 31744.0
            }, 
            {
                "y": 0.3537166519355448, 
                "x": 31808.0
            }, 
            {
                "y": 0.3536977760120211, 
                "x": 31872.0
            }, 
            {
                "y": 0.3537006492842619, 
                "x": 31936.0
            }, 
            {
                "y": 0.353719047037233, 
                "x": 32000.0
            }, 
            {
                "y": 0.3537001709772516, 
                "x": 32064.0
            }, 
            {
                "y": 0.35370304428840377, 
                "x": 32128.0
            }, 
            {
                "y": 0.35371521695995173, 
                "x": 32192.0
            }, 
            {
                "y": 0.35370256597491595, 
                "x": 32256.0
            }, 
            {
                "y": 0.35370543932498033, 
                "x": 32320.0
            }, 
            {
                "y": 0.353717612042207, 
                "x": 32384.0
            }, 
            {
                "y": 0.35369873606398244, 
                "x": 32448.0
            }, 
            {
                "y": 0.3537054008286769, 
                "x": 32512.0
            }, 
            {
                "y": 0.35370999060424047, 
                "x": 32576.0
            }, 
            {
                "y": 0.35370113104221446, 
                "x": 32640.0
            }, 
            {
                "y": 0.3537095122878321, 
                "x": 32704.0
            }, 
            {
                "y": 0.3537123856554408, 
                "x": 32768.0
            }, 
            {
                "y": 0.35369937610151864, 
                "x": 32832.0
            }, 
            {
                "y": 0.3537119073325548, 
                "x": 32896.0
            }, 
            {
                "y": 0.35371063066127684, 
                "x": 32960.0
            }, 
            {
                "y": 0.3536959046090996, 
                "x": 33024.0
            }, 
            {
                "y": 0.3537143024097125, 
                "x": 33088.0
            }, 
            {
                "y": 0.35371302572114527, 
                "x": 33152.0
            }, 
            {
                "y": 0.35370380761049536, 
                "x": 33216.0
            }, 
            {
                "y": 0.3536987395135844, 
                "x": 33280.0
            }, 
            {
                "y": 0.353717137162908, 
                "x": 33344.0
            }, 
            {
                "y": 0.353692394790635, 
                "x": 33408.0
            }, 
            {
                "y": 0.3537011344918631, 
                "x": 33472.0
            }, 
            {
                "y": 0.3537253987531689, 
                "x": 33536.0
            }, 
            {
                "y": 0.35369478972271345, 
                "x": 33600.0
            }, 
            {
                "y": 0.35370903742240567, 
                "x": 33664.0
            }, 
            {
                "y": 0.35370983576489917, 
                "x": 33728.0
            }, 
            {
                "y": 0.35369718468722533, 
                "x": 33792.0
            }, 
            {
                "y": 0.3537093574489096, 
                "x": 33856.0
            }, 
            {
                "y": 0.3537101557928476, 
                "x": 33920.0
            }, 
            {
                "y": 0.3536995796841713, 
                "x": 33984.0
            }, 
            {
                "y": 0.3537096774759925, 
                "x": 34048.0
            }, 
            {
                "y": 0.35371047582137527, 
                "x": 34112.0
            }, 
            {
                "y": 0.35369746634458993, 
                "x": 34176.0
            }, 
            {
                "y": 0.3537041310824932, 
                "x": 34240.0
            }, 
            {
                "y": 0.35371287087914666, 
                "x": 34304.0
            }, 
            {
                "y": 0.3536998613056267, 
                "x": 34368.0
            }, 
            {
                "y": 0.3537065260940641, 
                "x": 34432.0
            }, 
            {
                "y": 0.3537149072773894, 
                "x": 34496.0
            }, 
            {
                "y": 0.3536963898117309, 
                "x": 34560.0
            }, 
            {
                "y": 0.35370269616089217, 
                "x": 34624.0
            }, 
            {
                "y": 0.3537173023554507, 
                "x": 34688.0
            }, 
            {
                "y": 0.3536987847979122, 
                "x": 34752.0
            }, 
            {
                "y": 0.35371095759011545, 
                "x": 34816.0
            }, 
            {
                "y": 0.35371347231595196, 
                "x": 34880.0
            }, 
            {
                "y": 0.3536987464127885, 
                "x": 34944.0
            }, 
            {
                "y": 0.3537033362021449, 
                "x": 35008.0
            }, 
            {
                "y": 0.35371000095336175, 
                "x": 35072.0
            }, 
            {
                "y": 0.3537028578958007, 
                "x": 35136.0
            }, 
            {
                "y": 0.35369986475525067, 
                "x": 35200.0
            }, 
            {
                "y": 0.3537161874081356, 
                "x": 35264.0
            }, 
            {
                "y": 0.3536993864503621, 
                "x": 35328.0
            }, 
            {
                "y": 0.353702259748768, 
                "x": 35392.0
            }, 
            {
                "y": 0.35371443240535305, 
                "x": 35456.0
            }, 
            {
                "y": 0.353701781437402, 
                "x": 35520.0
            }, 
            {
                "y": 0.3536963549164053, 
                "x": 35584.0
            }, 
            {
                "y": 0.3537168274769833, 
                "x": 35648.0
            }, 
            {
                "y": 0.3536958766210094, 
                "x": 35712.0
            }, 
            {
                "y": 0.35370461629159944, 
                "x": 35776.0
            }, 
            {
                "y": 0.3537133561041838, 
                "x": 35840.0
            }, 
            {
                "y": 0.3536961966343136, 
                "x": 35904.0
            }, 
            {
                "y": 0.3537028613454258, 
                "x": 35968.0
            }, 
            {
                "y": 0.35371331747613044, 
                "x": 36032.0
            }, 
            {
                "y": 0.35369859157815553, 
                "x": 36096.0
            }, 
            {
                "y": 0.3536993898999768, 
                "x": 36160.0
            }, 
            {
                "y": 0.35371571253266193, 
                "x": 36224.0
            }, 
            {
                "y": 0.35369512008812415, 
                "x": 36288.0
            }, 
            {
                "y": 0.3537017848870634, 
                "x": 36352.0
            }, 
            {
                "y": 0.353716032565937, 
                "x": 36416.0
            }, 
            {
                "y": 0.3536975150571101, 
                "x": 36480.0
            }, 
            {
                "y": 0.35370382140907025, 
                "x": 36544.0
            }, 
            {
                "y": 0.35371842765923744, 
                "x": 36608.0
            }, 
            {
                "y": 0.35369747669332174, 
                "x": 36672.0
            }, 
            {
                "y": 0.35370034996069943, 
                "x": 36736.0
            }, 
            {
                "y": 0.35372082278497363, 
                "x": 36800.0
            }, 
            {
                "y": 0.3537036631229214, 
                "x": 36864.0
            }, 
            {
                "y": 0.35354020150845267, 
                "x": 36928.0
            }, 
            {
                "y": 0.35371112622935497, 
                "x": 36992.0
            }, 
            {
                "y": 0.3537157159824234, 
                "x": 37056.0
            }, 
            {
                "y": 0.3536892570713491, 
                "x": 37120.0
            }, 
            {
                "y": 0.3537072962600844, 
                "x": 37184.0
            }, 
            {
                "y": 0.35371396098431895, 
                "x": 37248.0
            }, 
            {
                "y": 0.3536916520006582, 
                "x": 37312.0
            }, 
            {
                "y": 0.3537096912747967, 
                "x": 37376.0
            }, 
            {
                "y": 0.35371635604956503, 
                "x": 37440.0
            }, 
            {
                "y": 0.3536916137347497, 
                "x": 37504.0
            }, 
            {
                "y": 0.3537062198661381, 
                "x": 37568.0
            }, 
            {
                "y": 0.35371460104510904, 
                "x": 37632.0
            }, 
            {
                "y": 0.3532854298310784, 
                "x": 37696.0
            }, 
            {
                "y": 0.353694806970625, 
                "x": 37760.0
            }, 
            {
                "y": 0.3537090546708485, 
                "x": 37824.0
            }, 
            {
                "y": 0.3537098530134199, 
                "x": 37888.0
            }, 
            {
                "y": 0.33285945101938574, 
                "x": 37952.0
            }, 
            {
                "y": 0.4971931884050217, 
                "x": 38016.0
            }, 
            {
                "y": 0.6612020399168356, 
                "x": 38048.0
            }, 
            {
                "y": 0.6611800946696218, 
                "x": 38080.0
            }, 
            {
                "y": 0.6619681236761057, 
                "x": 38112.0
            }, 
            {
                "y": 0.6625852242383714, 
                "x": 38144.0
            }, 
            {
                "y": 0.6631063075361631, 
                "x": 38176.0
            }, 
            {
                "y": 0.662721062849374, 
                "x": 38208.0
            }, 
            {
                "y": 0.6622161802809868, 
                "x": 38240.0
            }, 
            {
                "y": 0.6583898402406452, 
                "x": 38272.0
            }, 
            {
                "y": 0.6582005518398443, 
                "x": 38304.0
            }, 
            {
                "y": 0.6624575229645763, 
                "x": 38336.0
            }, 
            {
                "y": 0.6607812163757737, 
                "x": 38368.0
            }, 
            {
                "y": 0.6618240318480876, 
                "x": 38400.0
            }, 
            {
                "y": 0.6614706582898533, 
                "x": 38432.0
            }, 
            {
                "y": 0.6619206655453199, 
                "x": 38464.0
            }, 
            {
                "y": 0.661192685138581, 
                "x": 38496.0
            }, 
            {
                "y": 0.6607766262430635, 
                "x": 38528.0
            }, 
            {
                "y": 0.6609602947788049, 
                "x": 38560.0
            }, 
            {
                "y": 0.6558758726729939, 
                "x": 38592.0
            }, 
            {
                "y": 0.6603457679587952, 
                "x": 38624.0
            }, 
            {
                "y": 0.661824155705877, 
                "x": 38656.0
            }, 
            {
                "y": 0.6621343702223641, 
                "x": 38688.0
            }, 
            {
                "y": 0.6607969778093965, 
                "x": 38720.0
            }, 
            {
                "y": 0.6601609490024272, 
                "x": 38752.0
            }, 
            {
                "y": 0.6620021457184516, 
                "x": 38784.0
            }, 
            {
                "y": 0.6635425807864307, 
                "x": 38816.0
            }, 
            {
                "y": 0.6607337742206609, 
                "x": 38848.0
            }, 
            {
                "y": 0.6551123696287204, 
                "x": 38880.0
            }, 
            {
                "y": 0.6606096499657794, 
                "x": 38912.0
            }, 
            {
                "y": 0.6600369494096148, 
                "x": 38944.0
            }, 
            {
                "y": 0.6614954587957919, 
                "x": 38976.0
            }, 
            {
                "y": 0.6612474725506531, 
                "x": 39008.0
            }, 
            {
                "y": 0.6603228738299487, 
                "x": 39040.0
            }, 
            {
                "y": 0.6622270805920514, 
                "x": 39072.0
            }, 
            {
                "y": 0.6599982191723892, 
                "x": 39104.0
            }, 
            {
                "y": 0.6613311105611142, 
                "x": 39136.0
            }, 
            {
                "y": 0.6575125111918224, 
                "x": 39168.0
            }, 
            {
                "y": 0.4649045731417313, 
                "x": 39200.0
            }, 
            {
                "y": 0.40513608987933897, 
                "x": 39232.0
            }, 
            {
                "y": 0.8143444741343081, 
                "x": 39296.0
            }, 
            {
                "y": 0.8142291292819034, 
                "x": 39328.0
            }, 
            {
                "y": 0.813565218710169, 
                "x": 39360.0
            }, 
            {
                "y": 0.8138834378832467, 
                "x": 39392.0
            }, 
            {
                "y": 0.8136977845748478, 
                "x": 39424.0
            }, 
            {
                "y": 0.8132990182008724, 
                "x": 39456.0
            }, 
            {
                "y": 0.8122579328243903, 
                "x": 39488.0
            }, 
            {
                "y": 0.8124545957794652, 
                "x": 39520.0
            }, 
            {
                "y": 0.8128254518136786, 
                "x": 39552.0
            }, 
            {
                "y": 0.8131913581621948, 
                "x": 39584.0
            }, 
            {
                "y": 0.813617229006789, 
                "x": 39616.0
            }, 
            {
                "y": 0.8131164934112207, 
                "x": 39648.0
            }, 
            {
                "y": 0.813621485209002, 
                "x": 39680.0
            }, 
            {
                "y": 0.8138688113027855, 
                "x": 39712.0
            }, 
            {
                "y": 0.8128299261388915, 
                "x": 39744.0
            }, 
            {
                "y": 0.8133356330285172, 
                "x": 39776.0
            }, 
            {
                "y": 0.8129859252485309, 
                "x": 39808.0
            }, 
            {
                "y": 0.8129686175821996, 
                "x": 39840.0
            }, 
            {
                "y": 0.8132895897634439, 
                "x": 39872.0
            }, 
            {
                "y": 0.8131150593257515, 
                "x": 39904.0
            }, 
            {
                "y": 0.8129892683974342, 
                "x": 39936.0
            }, 
            {
                "y": 0.8131326292631906, 
                "x": 39968.0
            }, 
            {
                "y": 0.813371740526001, 
                "x": 40000.0
            }, 
            {
                "y": 0.8018828013426936, 
                "x": 40032.0
            }, 
            {
                "y": 0.8134514722820475, 
                "x": 40064.0
            }, 
            {
                "y": 0.8124341019372182, 
                "x": 40096.0
            }, 
            {
                "y": 0.8115768269653365, 
                "x": 40128.0
            }, 
            {
                "y": 0.8140299381862518, 
                "x": 40160.0
            }, 
            {
                "y": 0.8056884982648462, 
                "x": 40192.0
            }, 
            {
                "y": 0.807190232443852, 
                "x": 40224.0
            }, 
            {
                "y": 0.8131256913603069, 
                "x": 40256.0
            }, 
            {
                "y": 0.8065905544110203, 
                "x": 40288.0
            }, 
            {
                "y": 0.8099576837807646, 
                "x": 40320.0
            }, 
            {
                "y": 0.8061981024336625, 
                "x": 40352.0
            }, 
            {
                "y": 0.7953697882640338, 
                "x": 40384.0
            }, 
            {
                "y": 0.7945653169857646, 
                "x": 40416.0
            }, 
            {
                "y": 0.7915522142222386, 
                "x": 40448.0
            }, 
            {
                "y": 0.8127321072666767, 
                "x": 40480.0
            }, 
            {
                "y": 0.8100329568125928, 
                "x": 40512.0
            }, 
            {
                "y": 0.8070394367678331, 
                "x": 40544.0
            }, 
            {
                "y": 0.8125362514356423, 
                "x": 40576.0
            }, 
            {
                "y": 0.8130849713242676, 
                "x": 40608.0
            }, 
            {
                "y": 0.8126761392598132, 
                "x": 40640.0
            }, 
            {
                "y": 0.8078948556593575, 
                "x": 40672.0
            }, 
            {
                "y": 0.8128869467160521, 
                "x": 40704.0
            }, 
            {
                "y": 0.8120305532253893, 
                "x": 40736.0
            }, 
            {
                "y": 0.8062107358963638, 
                "x": 40768.0
            }, 
            {
                "y": 0.7771001592965281, 
                "x": 40800.0
            }, 
            {
                "y": 0.5072842550599134, 
                "x": 40832.0
            }, 
            {
                "y": 0.6323214428657896, 
                "x": 40864.0
            }, 
            {
                "y": 0.6587594749782486, 
                "x": 40896.0
            }, 
            {
                "y": 0.6602430912002007, 
                "x": 40928.0
            }, 
            {
                "y": 0.6609522287323599, 
                "x": 40960.0
            }, 
            {
                "y": 0.6625311551029845, 
                "x": 40992.0
            }, 
            {
                "y": 0.6639117219475297, 
                "x": 41024.0
            }, 
            {
                "y": 0.6669438889762317, 
                "x": 41056.0
            }, 
            {
                "y": 0.6448882843680083, 
                "x": 41088.0
            }, 
            {
                "y": 0.6457451083519267, 
                "x": 41120.0
            }, 
            {
                "y": 0.648255930248865, 
                "x": 41152.0
            }, 
            {
                "y": 0.6695506964669745, 
                "x": 41184.0
            }, 
            {
                "y": 0.6687403924523331, 
                "x": 41216.0
            }, 
            {
                "y": 0.6703238473529859, 
                "x": 41248.0
            }, 
            {
                "y": 0.6706528608624309, 
                "x": 41280.0
            }, 
            {
                "y": 0.6701316202958687, 
                "x": 41312.0
            }, 
            {
                "y": 0.6702346349116571, 
                "x": 41344.0
            }, 
            {
                "y": 0.6701266945437747, 
                "x": 41376.0
            }, 
            {
                "y": 0.6705924692970487, 
                "x": 41408.0
            }, 
            {
                "y": 0.657521133985882, 
                "x": 41440.0
            }, 
            {
                "y": 0.6706623973424004, 
                "x": 41472.0
            }, 
            {
                "y": 0.670490791989591, 
                "x": 41504.0
            }, 
            {
                "y": 0.6706692800529738, 
                "x": 41536.0
            }, 
            {
                "y": 0.6706084373428585, 
                "x": 41568.0
            }, 
            {
                "y": 0.670879368726403, 
                "x": 41600.0
            }, 
            {
                "y": 0.6706192245706134, 
                "x": 41632.0
            }, 
            {
                "y": 0.6686203057840837, 
                "x": 41664.0
            }, 
            {
                "y": 0.6134391856027998, 
                "x": 41696.0
            }, 
            {
                "y": 0.6404300417304265, 
                "x": 41728.0
            }, 
            {
                "y": 0.653111213443683, 
                "x": 41760.0
            }, 
            {
                "y": 0.6707243883309614, 
                "x": 41792.0
            }, 
            {
                "y": 0.662679454887775, 
                "x": 41824.0
            }, 
            {
                "y": 0.6698555461512629, 
                "x": 41856.0
            }, 
            {
                "y": 0.6704932619086664, 
                "x": 41888.0
            }, 
            {
                "y": 0.6681133217225689, 
                "x": 41920.0
            }, 
            {
                "y": 0.6707663828124719, 
                "x": 41952.0
            }, 
            {
                "y": 0.6690337211036917, 
                "x": 41984.0
            }, 
            {
                "y": 0.662799240074542, 
                "x": 42016.0
            }, 
            {
                "y": 0.4362910973538612, 
                "x": 42048.0
            }, 
            {
                "y": 0.815351313757931, 
                "x": 42112.0
            }, 
            {
                "y": 0.8150453190561606, 
                "x": 42144.0
            }, 
            {
                "y": 0.8149599782130261, 
                "x": 42176.0
            }, 
            {
                "y": 0.8143863434469745, 
                "x": 42208.0
            }, 
            {
                "y": 0.8139131466420985, 
                "x": 42240.0
            }, 
            {
                "y": 0.8140010837906175, 
                "x": 42272.0
            }, 
            {
                "y": 0.8146261542010113, 
                "x": 42304.0
            }, 
            {
                "y": 0.8145225279827842, 
                "x": 42336.0
            }, 
            {
                "y": 0.8146202811274157, 
                "x": 42368.0
            }, 
            {
                "y": 0.8149180775574052, 
                "x": 42400.0
            }, 
            {
                "y": 0.8140775648844122, 
                "x": 42432.0
            }, 
            {
                "y": 0.8145203278289423, 
                "x": 42464.0
            }, 
            {
                "y": 0.8148715362862142, 
                "x": 42496.0
            }, 
            {
                "y": 0.8143269683782406, 
                "x": 42528.0
            }, 
            {
                "y": 0.8146131282288509, 
                "x": 42560.0
            }, 
            {
                "y": 0.8148206257140715, 
                "x": 42592.0
            }, 
            {
                "y": 0.8141568196919627, 
                "x": 42624.0
            }, 
            {
                "y": 0.814543062774688, 
                "x": 42656.0
            }, 
            {
                "y": 0.8145892077506848, 
                "x": 42688.0
            }, 
            {
                "y": 0.8147737228440148, 
                "x": 42720.0
            }, 
            {
                "y": 0.8145646356184818, 
                "x": 42752.0
            }, 
            {
                "y": 0.8141893178094161, 
                "x": 42784.0
            }, 
            {
                "y": 0.8144065599330942, 
                "x": 42816.0
            }, 
            {
                "y": 0.8091072851886746, 
                "x": 42848.0
            }, 
            {
                "y": 0.8144102165932566, 
                "x": 42880.0
            }, 
            {
                "y": 0.8143042997986164, 
                "x": 42912.0
            }, 
            {
                "y": 0.8138421378857096, 
                "x": 42944.0
            }, 
            {
                "y": 0.812382654826182, 
                "x": 42976.0
            }, 
            {
                "y": 0.812612920056662, 
                "x": 43008.0
            }, 
            {
                "y": 0.8131537269679137, 
                "x": 43040.0
            }, 
            {
                "y": 0.8141487082565103, 
                "x": 43072.0
            }, 
            {
                "y": 0.8143848954461139, 
                "x": 43104.0
            }, 
            {
                "y": 0.8104663242539052, 
                "x": 43136.0
            }, 
            {
                "y": 0.8142625699651312, 
                "x": 43168.0
            }, 
            {
                "y": 0.8116790910743229, 
                "x": 43200.0
            }, 
            {
                "y": 0.7987001209824858, 
                "x": 43232.0
            }, 
            {
                "y": 0.8105204476487595, 
                "x": 43264.0
            }, 
            {
                "y": 0.8120553198667091, 
                "x": 43296.0
            }, 
            {
                "y": 0.8140019449022934, 
                "x": 43328.0
            }, 
            {
                "y": 0.8143367357789882, 
                "x": 43360.0
            }, 
            {
                "y": 0.8142936659793586, 
                "x": 43392.0
            }, 
            {
                "y": 0.8135270064655764, 
                "x": 43424.0
            }, 
            {
                "y": 0.8134866077816035, 
                "x": 43456.0
            }, 
            {
                "y": 0.8126095773559783, 
                "x": 43488.0
            }, 
            {
                "y": 0.814137998230307, 
                "x": 43520.0
            }, 
            {
                "y": 0.8144317431454026, 
                "x": 43552.0
            }, 
            {
                "y": 0.8141855779019667, 
                "x": 43584.0
            }, 
            {
                "y": 0.813706254520269, 
                "x": 43616.0
            }, 
            {
                "y": 0.501833120979921, 
                "x": 43648.0
            }
        ], 
        "name": "IPC"
    }
]